{"channels": {"UCyEJX-kSj0kOOCS7Qlq2G7g": {"name": "Arise News", "video_id": "4uHZdlX-DT4", "last_seen": "2026-02-26T07:00:46.855412"}, "UCgp4A6I8LCWrhUzn-5SbKvA": {"name": "TVC News Nigeria", "video_id": "b-Yzp0l8cAM", "last_seen": "2026-02-26T07:00:51.682991"}, "UCEXGDNclvmg6RW0vipJYsTQ": {"name": "Channels Television", "video_id": "d4zDorDl5UE", "last_seen": "2026-02-26T07:00:58.083214"}, "UCPLKy4Ypb4mfblbjJI8Aljw": {"name": "News Central TV", "video_id": "puZ8rz7_4UY", "last_seen": "2026-02-26T07:01:03.190570"}, "UCaiRlJZKn0bMRNutRWArrrg": {"name": "NTA Live", "video_id": "48FhKecDhyE", "last_seen": "2026-02-26T07:01:09.165333"}, "UCNuPuew8lLVB3mMAm9_Qt9w": {"name": "Silverbird N24", "video_id": "MYnlNaMz_dA", "last_seen": "2026-02-26T07:01:14.001861"}, "UCC54ckTvq2EphHOiM5iPFzg": {"name": "Voice of the People 90.3 FM", "video_id": "K2CNj4GIA-w", "last_seen": "2026-02-26T07:01:25.337587"}, "UChd1DEecCRlxaa0-hvPACCw": {"name": "JoyNews", "video_id": "n4ThGAoXtyE", "last_seen": "2026-02-26T07:01:31.279234"}, "UCKlgbbF9wphTKATOWiG5jPQ": {"name": "Adom TV", "video_id": "aUCB1AWfubU", "last_seen": "2026-02-26T07:01:45.400834"}, "UCWJMPKmFc1RIem7_3BUcjPQ": {"name": "AITLiveStream1", "video_id": "ae4m9b8l4dQ", "last_seen": "2026-02-26T07:01:18.218410"}, "UC9VSDs4ZXo3sjOoPkmW2iRQ": {"name": "TV3 Ghana", "video_id": "0BaFc0oI3Tw", "last_seen": "2026-02-26T07:01:35.852511"}, "UCP5-atAAZsIOscm-4EkL9nQ": {"name": "Parliament of Ghana", "video_id": "kFTgb3Vnj18", "last_seen": "2026-02-25T19:07:45.754586"}}, "logos": {}}